holmes_rs/__init__.py
holmes_rs/__init__.pyi
holmes_rs/calibration/__init__.pyi
holmes_rs/calibration/sce.pyi
holmes_rs/holmes_rs.cpython-312-darwin.so
holmes_rs/hydro/__init__.pyi
holmes_rs/hydro/bucket.pyi
holmes_rs/hydro/cequeau.pyi
holmes_rs/hydro/gr4j.pyi
holmes_rs/metrics.pyi
holmes_rs/pet/__init__.pyi
holmes_rs/pet/oudin.pyi
holmes_rs/snow/__init__.pyi
holmes_rs/snow/cemaneige.pyi
holmes_rs-0.3.0.dist-info/METADATA
holmes_rs-0.3.0.dist-info/WHEEL
holmes_rs-0.3.0.dist-info/licenses/LICENSE
holmes_rs-0.3.0.dist-info/RECORD
