Metadata-Version: 2.4
Name: holmes-rs
Version: 0.3.0
Classifier: Development Status :: 3 - Alpha
Classifier: Intended Audience :: Education
Classifier: Programming Language :: Python :: 3
Classifier: Programming Language :: Python :: 3.11
Classifier: Programming Language :: Python :: 3.12
Classifier: Programming Language :: Python :: 3.13
Classifier: Operating System :: OS Independent
Classifier: Topic :: Scientific/Engineering :: Hydrology
License-File: LICENSE
Summary: HOLMES (HydrOLogical Modeling Educationnal Software) is a software developped to teach operational hydrology. It is developed at the university Laval, Québec, Canada. These are the models written in rust.
Author-email: Antoine Lefebvre-Brossard <antoinelb@proton.me>
License: MIT
Requires-Python: >=3.11
Project-URL: Homepage, https://github.com/antoinelb/holmes
Project-URL: Repository, https://github.com/antoinelb/holmes
